{
  "version": "3.3.4",
  "flags": {},
  "shapes": [
    {
      "kie_linking": [],
      "label": "canvas",
      "score": null,
      "points": [
        [
          508.9,
          14.0
        ],
        [
          756.5495207667732,
          14.0
        ],
        [
          756.5495207667732,
          268.9456869009585
        ],
        [
          508.9,
          268.9456869009585
        ]
      ],
      "group_id": 1,
      "description": "",
      "difficult": false,
      "shape_type": "rectangle",
      "flags": {},
      "attributes": {}
    },
    {
      "kie_linking": [],
      "label": "point_tl",
      "score": null,
      "points": [
        [
          539.1,
          65.9
        ]
      ],
      "group_id": 1,
      "description": "",
      "difficult": false,
      "shape_type": "point",
      "flags": {},
      "attributes": {}
    },
    {
      "kie_linking": [],
      "label": "point_tr",
      "score": null,
      "points": [
        [
          712.8,
          37.9
        ]
      ],
      "group_id": 1,
      "description": "",
      "difficult": false,
      "shape_type": "point",
      "flags": {},
      "attributes": {}
    },
    {
      "kie_linking": [],
      "label": "point_br",
      "score": null,
      "points": [
        [
          726.4,
          220.9
        ]
      ],
      "group_id": 1,
      "description": "",
      "difficult": false,
      "shape_type": "point",
      "flags": {},
      "attributes": {}
    },
    {
      "kie_linking": [],
      "label": "point_bl",
      "score": null,
      "points": [
        [
          567.9,
          240.8
        ]
      ],
      "group_id": 1,
      "description": "",
      "difficult": false,
      "shape_type": "point",
      "flags": {},
      "attributes": {}
    }
  ],
  "imagePath": "20260103_162903_742.png",
  "imageData": null,
  "imageHeight": 720,
  "imageWidth": 1280,
  "description": ""
}