{
  "version": "3.3.4",
  "flags": {},
  "shapes": [
    {
      "kie_linking": [],
      "label": "canvas",
      "score": null,
      "points": [
        [
          293.0232558139535,
          267.9606440071556
        ],
        [
          483.8998211091234,
          267.9606440071556
        ],
        [
          483.8998211091234,
          428.78354203935595
        ],
        [
          293.0232558139535,
          428.78354203935595
        ]
      ],
      "group_id": 1,
      "description": "",
      "difficult": false,
      "shape_type": "rectangle",
      "flags": {},
      "attributes": {}
    },
    {
      "kie_linking": [],
      "label": "point_tl",
      "score": null,
      "points": [
        [
          324.5080500894454,
          284.0608228980322
        ]
      ],
      "group_id": 1,
      "description": "",
      "difficult": false,
      "shape_type": "point",
      "flags": {},
      "attributes": {}
    },
    {
      "kie_linking": [],
      "label": "point_tr",
      "score": null,
      "points": [
        [
          457.9952267303102,
          290.9069212410501
        ]
      ],
      "group_id": 1,
      "description": "",
      "difficult": false,
      "shape_type": "point",
      "flags": {},
      "attributes": {}
    },
    {
      "kie_linking": [],
      "label": "point_br",
      "score": null,
      "points": [
        [
          459.96388026692733,
          402.7803228574722
        ]
      ],
      "group_id": 1,
      "description": "",
      "difficult": false,
      "shape_type": "point",
      "flags": {},
      "attributes": {}
    },
    {
      "kie_linking": [],
      "label": "point_bl",
      "score": null,
      "points": [
        [
          318.60465116279073,
          409.6422182468694
        ]
      ],
      "group_id": 1,
      "description": "",
      "difficult": false,
      "shape_type": "point",
      "flags": {},
      "attributes": {}
    }
  ],
  "imagePath": "20260103_162741_375.png",
  "imageData": null,
  "imageHeight": 720,
  "imageWidth": 1280
}