{
  "version": "3.3.4",
  "flags": {},
  "shapes": [
    {
      "kie_linking": [],
      "label": "canvas",
      "score": null,
      "points": [
        [
          594.022988505747,
          159.8599137931035
        ],
        [
          962.4137931034481,
          159.8599137931035
        ],
        [
          962.4137931034481,
          632.7011494252873
        ],
        [
          594.022988505747,
          632.7011494252873
        ]
      ],
      "group_id": 1,
      "description": "",
      "difficult": false,
      "shape_type": "rectangle",
      "flags": {},
      "attributes": {}
    },
    {
      "kie_linking": [],
      "label": "point_tl",
      "score": null,
      "points": [
        [
          685.2439024390244,
          230.12195121951217
        ]
      ],
      "group_id": 1,
      "description": "",
      "difficult": false,
      "shape_type": "point",
      "flags": {},
      "attributes": {}
    },
    {
      "kie_linking": [],
      "label": "point_tr",
      "score": null,
      "points": [
        [
          929.1329479768785,
          297.80346820809245
        ]
      ],
      "group_id": 1,
      "description": "",
      "difficult": false,
      "shape_type": "point",
      "flags": {},
      "attributes": {}
    },
    {
      "kie_linking": [],
      "label": "point_br",
      "score": null,
      "points": [
        [
          918.6799065420561,
          582.9439252336448
        ]
      ],
      "group_id": 1,
      "description": "",
      "difficult": false,
      "shape_type": "point",
      "flags": {},
      "attributes": {}
    },
    {
      "kie_linking": [],
      "label": "point_bl",
      "score": null,
      "points": [
        [
          649.1247264770241,
          574.4967177242887
        ]
      ],
      "group_id": 1,
      "description": "",
      "difficult": false,
      "shape_type": "point",
      "flags": {},
      "attributes": {}
    }
  ],
  "imagePath": "20260104_213137_631.png",
  "imageData": null,
  "imageHeight": 720,
  "imageWidth": 1280
}