{
  "version": "3.3.4",
  "flags": {},
  "shapes": [
    {
      "kie_linking": [],
      "label": "canvas",
      "score": null,
      "points": [
        [
          413.5731796351355,
          96.57036649857201
        ],
        [
          820.2197802197802,
          96.57036649857201
        ],
        [
          820.2197802197802,
          511.53846153846155
        ],
        [
          413.5731796351355,
          511.53846153846155
        ]
      ],
      "group_id": 1,
      "description": "",
      "difficult": false,
      "shape_type": "rectangle",
      "flags": {},
      "attributes": {}
    },
    {
      "kie_linking": [],
      "label": "point_tl",
      "score": null,
      "points": [
        [
          500.1113585746102,
          151.7594654788419
        ]
      ],
      "group_id": 1,
      "description": "",
      "difficult": false,
      "shape_type": "point",
      "flags": {},
      "attributes": {}
    },
    {
      "kie_linking": [],
      "label": "point_tr",
      "score": null,
      "points": [
        [
          767.6,
          198.1
        ]
      ],
      "group_id": 1,
      "description": "",
      "difficult": false,
      "shape_type": "point",
      "flags": {},
      "attributes": {}
    },
    {
      "kie_linking": [],
      "label": "point_br",
      "score": null,
      "points": [
        [
          710.1,
          461.35054945054947
        ]
      ],
      "group_id": 1,
      "description": "",
      "difficult": false,
      "shape_type": "point",
      "flags": {},
      "attributes": {}
    },
    {
      "kie_linking": [],
      "label": "point_bl",
      "score": null,
      "points": [
        [
          459.8843930635838,
          410.5202312138728
        ]
      ],
      "group_id": 1,
      "description": "",
      "difficult": false,
      "shape_type": "point",
      "flags": {},
      "attributes": {}
    }
  ],
  "imagePath": "20260104_215017_227.png",
  "imageData": null,
  "imageHeight": 720,
  "imageWidth": 1280
}