{
  "version": "3.3.4",
  "flags": {},
  "shapes": [
    {
      "kie_linking": [],
      "label": "canvas",
      "score": null,
      "points": [
        [
          215.47711729530772,
          17.904448750284217
        ],
        [
          726.4341085271317,
          17.904448750284217
        ],
        [
          726.4341085271317,
          515.0387596899226
        ],
        [
          215.47711729530772,
          515.0387596899226
        ]
      ],
      "group_id": 1,
      "description": "",
      "difficult": false,
      "shape_type": "rectangle",
      "flags": {},
      "attributes": {}
    },
    {
      "kie_linking": [],
      "label": "point_tl",
      "score": null,
      "points": [
        [
          282.4324324324324,
          71.62162162162161
        ]
      ],
      "group_id": 1,
      "description": "",
      "difficult": false,
      "shape_type": "point",
      "flags": {},
      "attributes": {}
    },
    {
      "kie_linking": [],
      "label": "point_tr",
      "score": null,
      "points": [
        [
          667.2504091653028,
          117.6759410801964
        ]
      ],
      "group_id": 1,
      "description": "",
      "difficult": false,
      "shape_type": "point",
      "flags": {},
      "attributes": {}
    },
    {
      "kie_linking": [],
      "label": "point_br",
      "score": null,
      "points": [
        [
          632.4954371504266,
          472.95260523991755
        ]
      ],
      "group_id": 1,
      "description": "",
      "difficult": false,
      "shape_type": "point",
      "flags": {},
      "attributes": {}
    },
    {
      "kie_linking": [],
      "label": "point_bl",
      "score": null,
      "points": [
        [
          283.1435079726652,
          441.20728929384967
        ]
      ],
      "group_id": 1,
      "description": "",
      "difficult": false,
      "shape_type": "point",
      "flags": {},
      "attributes": {}
    }
  ],
  "imagePath": "20260104_214931_181.png",
  "imageData": null,
  "imageHeight": 720,
  "imageWidth": 1280
}